pyfirmata_epd/__init__.py
pyfirmata_epd/epd.py
pyfirmata_epd/epdpaint.py
pyfirmata_epd/fonts.py
pyfirmata_epd-1.0.1.dist-info/LICENSE
pyfirmata_epd-1.0.1.dist-info/METADATA
pyfirmata_epd-1.0.1.dist-info/WHEEL
pyfirmata_epd-1.0.1.dist-info/top_level.txt
pyfirmata_epd-1.0.1.dist-info/RECORD
