Metadata-Version: 2.2
Name: pyfirmata_epd
Version: 1.0.1
Summary: A library to create and send image data to an ePaper display connected to a Firmata powered microcontroller. Supports both pyFirmata and pyFirmata2!
Author-email: Miniontoby <author@example.com>
Project-URL: Homepage, https://github.com/Miniontoby/pyFirmata_epd
Project-URL: Documentation, https://pyfirmata_epd.readthedocs.io/en/latest/
Project-URL: Repository, https://github.com/Miniontoby/pyFirmata_epd.git
Project-URL: Bug Tracker, https://github.com/Miniontoby/pyFirmata_epd/issues
Keywords: pyfirmata,pyfirmata2,epaper,waveshare
Classifier: Development Status :: 5 - Production/Stable
Classifier: Intended Audience :: Developers
Classifier: Operating System :: OS Independent
Classifier: Programming Language :: Python :: 2.3
Classifier: Programming Language :: Python :: 3
Classifier: Programming Language :: Python :: 3.6
Classifier: Programming Language :: Python :: 3.7
Classifier: Programming Language :: Python :: 3.8
Classifier: Programming Language :: Python :: 3.9
Classifier: Programming Language :: Python :: 3.10
Classifier: Programming Language :: Python :: 3.11
Requires-Python: >=2.3
License-File: LICENSE
Provides-Extra: pyfirmata
Requires-Dist: pyFirmata; extra == "pyfirmata"
Provides-Extra: pyfirmata2
Requires-Dist: pyFirmata2; extra == "pyfirmata2"
